snakealtpromoter/_version.py
snakealtpromoter/cli.py
snakealtpromoter/data/Human_GSM4421328_Human_Left_Ventrice_Tissue_Healthy_cDNA_PAIRED_SRR11351704_R1.fastq.gz
snakealtpromoter/data/Human_GSM4421328_Human_Left_Ventrice_Tissue_Healthy_cDNA_PAIRED_SRR11351704_R2.fastq.gz
snakealtpromoter/data/Human_GSM4421329_Human_Left_Ventrice_Tissue_Healthy_cDNA_PAIRED_SRR11351705_R1.fastq.gz
snakealtpromoter/data/Human_GSM4421329_Human_Left_Ventrice_Tissue_Healthy_cDNA_PAIRED_SRR11351705_R2.fastq.gz
snakealtpromoter/data/Human_GSM4421331_Human_Left_Ventrice_Tissue_Heart_Failure_cDNA_PAIRED_SRR11351707_R1.fastq.gz
snakealtpromoter/data/Human_GSM4421331_Human_Left_Ventrice_Tissue_Heart_Failure_cDNA_PAIRED_SRR11351707_R2.fastq.gz
snakealtpromoter/data/Human_GSM4421332_Human_Left_Ventrice_Tissue_Heart_Failure_cDNA_PAIRED_SRR11351708_R1.fastq.gz
snakealtpromoter/data/Human_GSM4421332_Human_Left_Ventrice_Tissue_Heart_Failure_cDNA_PAIRED_SRR11351708_R2.fastq.gz
snakealtpromoter/data/hg38.fa
snakealtpromoter/data/hg38.gtf
snakealtpromoter/data/samplesheet/Heart_CAGE.tsv
snakealtpromoter/data/samplesheet/Heart_RNAseq.tsv
snakealtpromoter/data/samplesheet/samplesheet.tsv
snakealtpromoter/docs/Genomesetup.md
snakealtpromoter/docs/Snakealtpromoter.md
snakealtpromoter/docs/workflow_overview.png
snakealtpromoter/rules/Genomesetup.Snakefile
snakealtpromoter/rules/Snakealtpromoter.Snakefile
snakealtpromoter/rules/envs/altbasic.yaml
snakealtpromoter/rules/envs/altbasicR.yaml
snakealtpromoter/rules/envs/altbasicRlimma.yaml
snakealtpromoter/rules/envs/bam.yaml
snakealtpromoter/rules/envs/basic.yaml
snakealtpromoter/rules/envs/dexR.yaml
snakealtpromoter/rules/envs/featurecounts.yaml
snakealtpromoter/rules/envs/r.yaml
snakealtpromoter/scripts/CAGE_bam.R
snakealtpromoter/scripts/CAGE_count.R
snakealtpromoter/scripts/RNANEW_test_unchanged_plots_tsne_only.R
snakealtpromoter/scripts/compare_different_methods.R
snakealtpromoter/scripts/data_download.R
snakealtpromoter/scripts/dexseq_counts_separate.R
snakealtpromoter-1.0.5.dist-info/licenses/LICENSE.md
snakealtpromoter-1.0.5.dist-info/METADATA
snakealtpromoter-1.0.5.dist-info/WHEEL
snakealtpromoter-1.0.5.dist-info/entry_points.txt
snakealtpromoter-1.0.5.dist-info/top_level.txt
snakealtpromoter-1.0.5.dist-info/RECORD
