Metadata-Version: 2.4
Name: SnakeAltPromoter
Version: 1.0.5
Summary: A Snakemake pipeline for alternative promoter analysis
Home-page: https://github.com/YidanSunResearchLab/SnakeAltPromoter
Author: Yidan Sun
Author-email: Yidan Sun <syidan@wustl.edu>
Maintainer-email: Jared Lalmansingh <jared.lalmansingh@wustl.edu>
License: Copyright (c) 2025 Yidan Sun
Project-URL: homepage, https://github.com/YidanSunResearchLab/SnakeAltPromoter
Project-URL: repository, https://github.com/YidanSunResearchLab/SnakeAltPromoter
Project-URL: issues, https://github.com/YidanSunResearchLab/SnakeAltPromoter/issues
Classifier: Programming Language :: Python :: 3.11
Classifier: Operating System :: POSIX
Classifier: Intended Audience :: Science/Research
Classifier: Topic :: Scientific/Engineering :: Bio-Informatics
Requires-Python: >=3.11
License-File: LICENSE.md
Requires-Dist: snakemake>=8.28.0
Requires-Dist: streamlit
Requires-Dist: pyarrow
Requires-Dist: pandas
Dynamic: author
Dynamic: home-page
Dynamic: license-file
Dynamic: requires-python
